[
  {
    "timestamp": "2026-03-26T09:12:33.881056",
    "user": "Пользователь",
    "type": "PROJECT_OPEN",
    "description": "Открыт проект: C:/Users/oniki/Desktop/ФОТсо статистикой/Для тестов.tabelproj"
  },
  {
    "timestamp": "2026-03-26T09:18:48.712123",
    "user": "Пользователь",
    "type": "PROJECT_OPEN",
    "description": "Открыт проект: C:/Users/oniki/Desktop/ФОТсо статистикой/Для тестов.tabelproj"
  },
  {
    "timestamp": "2026-03-26T09:48:27.700106",
    "user": "Пользователь",
    "type": "PROJECT_OPEN",
    "description": "Открыт проект: C:/Users/oniki/Desktop/ФОТсо статистикой/Для тестов.tabelproj"
  },
  {
    "timestamp": "2026-03-26T10:07:07.142696",
    "user": "Пользователь",
    "type": "PROJECT_OPEN",
    "description": "Открыт проект: C:/Users/oniki/Desktop/ФОТсо статистикой/Для тестов.tabelproj"
  },
  {
    "timestamp": "2026-03-26T10:07:17.645980",
    "user": "Пользователь",
    "type": "PROJECT_SAVE",
    "description": "Сохранён проект: C:/Users/oniki/Desktop/project_root2/123.tabelproj"
  },
  {
    "timestamp": "2026-03-26T10:07:17.646514",
    "user": "Пользователь",
    "type": "PROJECT_SAVE_AS",
    "description": "Сохранён проект как: C:/Users/oniki/Desktop/project_root2/123.tabelproj"
  },
  {
    "timestamp": "2026-03-26T10:09:53.684011",
    "user": "Пользователь",
    "type": "PROJECT_OPEN",
    "description": "Автозагрузка последнего проекта: C:/Users/oniki/Desktop/project_root2/123.tabelproj"
  },
  {
    "timestamp": "2026-03-26T10:16:25.977775",
    "user": "Пользователь",
    "type": "PROJECT_OPEN",
    "description": "Автозагрузка последнего проекта: C:/Users/oniki/Desktop/project_root2/123.tabelproj"
  },
  {
    "timestamp": "2026-03-26T10:39:22.443636",
    "user": "Пользователь",
    "type": "PROJECT_OPEN",
    "description": "Автозагрузка последнего проекта: C:/Users/oniki/Desktop/project_root2/123.tabelproj"
  },
  {
    "timestamp": "2026-03-26T10:43:48.397859",
    "user": "Пользователь",
    "type": "PROJECT_OPEN",
    "description": "Автозагрузка последнего проекта: C:/Users/oniki/Desktop/project_root2/123.tabelproj"
  },
  {
    "timestamp": "2026-03-26T10:45:34.031177",
    "user": "Пользователь",
    "type": "PROJECT_OPEN",
    "description": "Автозагрузка последнего проекта: C:/Users/oniki/Desktop/project_root2/123.tabelproj"
  },
  {
    "timestamp": "2026-03-26T10:47:00.052355",
    "user": "Пользователь",
    "type": "PROJECT_OPEN",
    "description": "Автозагрузка последнего проекта: C:/Users/oniki/Desktop/project_root2/123.tabelproj"
  },
  {
    "timestamp": "2026-03-26T10:56:35.691217",
    "user": "Пользователь",
    "type": "PROJECT_OPEN",
    "description": "Автозагрузка последнего проекта: C:/Users/oniki/Desktop/project_root2/123.tabelproj"
  },
  {
    "timestamp": "2026-03-26T10:58:11.200725",
    "user": "Пользователь",
    "type": "PROJECT_OPEN",
    "description": "Автозагрузка последнего проекта: C:/Users/oniki/Desktop/project_root2/123.tabelproj"
  },
  {
    "timestamp": "2026-03-26T10:59:32.359624",
    "user": "Пользователь",
    "type": "PROJECT_OPEN",
    "description": "Автозагрузка последнего проекта: C:/Users/oniki/Desktop/project_root2/123.tabelproj"
  },
  {
    "timestamp": "2026-03-26T11:18:36.913752",
    "user": "Пользователь",
    "type": "PROJECT_OPEN",
    "description": "Автозагрузка последнего проекта: C:/Users/oniki/Desktop/project_root2/123.tabelproj"
  },
  {
    "timestamp": "2026-03-26T11:19:08.509625",
    "user": "Пользователь",
    "type": "PROJECT_OPEN",
    "description": "Автозагрузка последнего проекта: C:/Users/oniki/Desktop/project_root2/123.tabelproj"
  },
  {
    "timestamp": "2026-03-26T11:21:15.520483",
    "user": "Пользователь",
    "type": "PROJECT_OPEN",
    "description": "Автозагрузка последнего проекта: C:/Users/oniki/Desktop/project_root2/123.tabelproj"
  },
  {
    "timestamp": "2026-03-26T11:35:41.449587",
    "user": "Пользователь",
    "type": "PROJECT_OPEN",
    "description": "Автозагрузка последнего проекта: C:/Users/oniki/Desktop/project_root2/123.tabelproj"
  },
  {
    "timestamp": "2026-03-26T11:37:33.271444",
    "user": "Пользователь",
    "type": "PROJECT_OPEN",
    "description": "Автозагрузка последнего проекта: C:/Users/oniki/Desktop/project_root2/123.tabelproj"
  },
  {
    "timestamp": "2026-03-26T11:38:57.792039",
    "user": "Пользователь",
    "type": "PROJECT_OPEN",
    "description": "Открыт проект: C:/Users/oniki/Desktop/ФОТсо статистикой/2026.tabelproj"
  },
  {
    "timestamp": "2026-03-26T11:42:35.566044",
    "user": "Пользователь",
    "type": "PROJECT_OPEN",
    "description": "Автозагрузка последнего проекта: C:/Users/oniki/Desktop/project_root2/123.tabelproj"
  },
  {
    "timestamp": "2026-03-26T11:47:19.544233",
    "user": "Пользователь",
    "type": "PROJECT_OPEN",
    "description": "Автозагрузка последнего проекта: C:/Users/oniki/Desktop/project_root2/123.tabelproj"
  },
  {
    "timestamp": "2026-03-26T11:49:45.586297",
    "user": "Пользователь",
    "type": "PROJECT_OPEN",
    "description": "Автозагрузка последнего проекта: C:/Users/oniki/Desktop/project_root2/123.tabelproj"
  },
  {
    "timestamp": "2026-03-26T11:50:40.747027",
    "user": "Пользователь",
    "type": "PROJECT_SAVE",
    "description": "Сохранён проект: C:/Users/oniki/Desktop/project_root2/123.tabelproj"
  },
  {
    "timestamp": "2026-03-26T11:50:46.341045",
    "user": "Пользователь",
    "type": "PROJECT_OPEN",
    "description": "Автозагрузка последнего проекта: C:/Users/oniki/Desktop/project_root2/123.tabelproj"
  },
  {
    "timestamp": "2026-03-26T11:52:05.796004",
    "user": "Пользователь",
    "type": "PROJECT_OPEN",
    "description": "Автозагрузка последнего проекта: C:/Users/oniki/Desktop/project_root2/123.tabelproj"
  },
  {
    "timestamp": "2026-03-26T11:54:09.906716",
    "user": "Пользователь",
    "type": "PROJECT_OPEN",
    "description": "Автозагрузка последнего проекта: C:/Users/oniki/Desktop/project_root2/123.tabelproj"
  },
  {
    "timestamp": "2026-03-26T11:56:36.382181",
    "user": "Пользователь",
    "type": "PROJECT_OPEN",
    "description": "Автозагрузка последнего проекта: C:/Users/oniki/Desktop/project_root2/123.tabelproj"
  },
  {
    "timestamp": "2026-03-26T11:56:55.687331",
    "user": "Пользователь",
    "type": "PROJECT_OPEN",
    "description": "Автозагрузка последнего проекта: C:/Users/oniki/Desktop/project_root2/123.tabelproj"
  },
  {
    "timestamp": "2026-03-26T11:57:17.493851",
    "user": "Пользователь",
    "type": "PROJECT_OPEN",
    "description": "Автозагрузка последнего проекта: C:/Users/oniki/Desktop/project_root2/123.tabelproj"
  },
  {
    "timestamp": "2026-03-26T11:59:37.851808",
    "user": "Пользователь",
    "type": "PROJECT_OPEN",
    "description": "Автозагрузка последнего проекта: C:/Users/oniki/Desktop/project_root2/123.tabelproj"
  },
  {
    "timestamp": "2026-03-26T12:00:24.100534",
    "user": "Пользователь",
    "type": "PROJECT_OPEN",
    "description": "Автозагрузка последнего проекта: C:/Users/oniki/Desktop/project_root2/123.tabelproj"
  },
  {
    "timestamp": "2026-03-26T12:03:07.599151",
    "user": "Пользователь",
    "type": "PROJECT_OPEN",
    "description": "Автозагрузка последнего проекта: C:/Users/oniki/Desktop/project_root2/123.tabelproj"
  },
  {
    "timestamp": "2026-03-26T12:05:57.587085",
    "user": "Пользователь",
    "type": "PROJECT_OPEN",
    "description": "Автозагрузка последнего проекта: C:/Users/oniki/Desktop/project_root2/123.tabelproj"
  },
  {
    "timestamp": "2026-03-26T12:25:54.424644",
    "user": "Пользователь",
    "type": "PROJECT_OPEN",
    "description": "Автозагрузка последнего проекта: C:/Users/oniki/Desktop/project_root2/123.tabelproj"
  },
  {
    "timestamp": "2026-03-26T12:52:36.407467",
    "user": "Пользователь",
    "type": "PROJECT_OPEN",
    "description": "Автозагрузка последнего проекта: C:/Users/oniki/Desktop/project_root2/123.tabelproj"
  },
  {
    "timestamp": "2026-03-26T13:16:13.131176",
    "user": "Пользователь",
    "type": "PROJECT_OPEN",
    "description": "Автозагрузка последнего проекта: C:/Users/oniki/Desktop/project_root2/123.tabelproj"
  },
  {
    "timestamp": "2026-03-26T13:17:48.062024",
    "user": "Пользователь",
    "type": "PROJECT_OPEN",
    "description": "Автозагрузка последнего проекта: C:/Users/oniki/Desktop/project_root2/123.tabelproj"
  },
  {
    "timestamp": "2026-03-26T14:35:18.238642",
    "user": "Пользователь",
    "type": "PROJECT_OPEN",
    "description": "Автозагрузка последнего проекта: C:/Users/oniki/Desktop/project_root2/123.tabelproj"
  },
  {
    "timestamp": "2026-03-26T14:37:24.104413",
    "user": "Пользователь",
    "type": "PROJECT_OPEN",
    "description": "Автозагрузка последнего проекта: C:/Users/oniki/Desktop/project_root2/123.tabelproj"
  },
  {
    "timestamp": "2026-03-26T15:33:04.940006",
    "user": "Пользователь",
    "type": "PROJECT_OPEN",
    "description": "Автозагрузка последнего проекта: C:/Users/oniki/Desktop/project_root2/123.tabelproj"
  },
  {
    "timestamp": "2026-03-26T15:42:16.476290",
    "user": "Пользователь",
    "type": "PROJECT_OPEN",
    "description": "Автозагрузка последнего проекта: C:/Users/oniki/Desktop/project_root2/123.tabelproj"
  },
  {
    "timestamp": "2026-03-26T15:42:59.241175",
    "user": "Пользователь",
    "type": "PROJECT_SAVE",
    "description": "Сохранён проект: C:/Users/oniki/Desktop/project_root2/123.tabelproj"
  },
  {
    "timestamp": "2026-03-26T15:59:02.092612",
    "user": "Пользователь",
    "type": "PROJECT_OPEN",
    "description": "Автозагрузка последнего проекта: C:/Users/oniki/Desktop/project_root2/123.tabelproj"
  },
  {
    "timestamp": "2026-03-26T16:07:39.771113",
    "user": "Пользователь",
    "type": "PROJECT_OPEN",
    "description": "Автозагрузка последнего проекта: C:/Users/oniki/Desktop/project_root2/123.tabelproj"
  },
  {
    "timestamp": "2026-03-26T16:08:10.035463",
    "user": "Пользователь",
    "type": "PROJECT_OPEN",
    "description": "Автозагрузка последнего проекта: C:/Users/oniki/Desktop/project_root2/123.tabelproj"
  },
  {
    "timestamp": "2026-03-26T16:13:53.236514",
    "user": "Пользователь",
    "type": "PROJECT_OPEN",
    "description": "Автозагрузка последнего проекта: C:/Users/oniki/Desktop/project_root2/123.tabelproj"
  },
  {
    "timestamp": "2026-03-26T16:58:16.778089",
    "user": "Пользователь",
    "type": "PROJECT_OPEN",
    "description": "Автозагрузка последнего проекта: C:/Users/oniki/Desktop/project_root2/123.tabelproj"
  },
  {
    "timestamp": "2026-03-27T13:47:34.544986",
    "user": "Пользователь",
    "type": "PROJECT_OPEN",
    "description": "Автозагрузка последнего проекта: C:/Users/oniki/Desktop/project_root2/123.tabelproj"
  },
  {
    "timestamp": "2026-03-27T14:22:49.235912",
    "user": "Пользователь",
    "type": "PROJECT_OPEN",
    "description": "Автозагрузка последнего проекта: C:/Users/oniki/Desktop/project_root2/123.tabelproj"
  },
  {
    "timestamp": "2026-03-27T15:18:28.790217",
    "user": "Пользователь",
    "type": "PROJECT_OPEN",
    "description": "Автозагрузка последнего проекта: C:/Users/oniki/Desktop/project_root2/123.tabelproj"
  },
  {
    "timestamp": "2026-03-27T15:27:15.110641",
    "user": "Пользователь",
    "type": "PROJECT_OPEN",
    "description": "Автозагрузка последнего проекта: C:/Users/oniki/Desktop/project_root2/123.tabelproj"
  },
  {
    "timestamp": "2026-03-27T15:35:38.923453",
    "user": "Пользователь",
    "type": "PROJECT_OPEN",
    "description": "Автозагрузка последнего проекта: C:/Users/oniki/Desktop/project_root2/123.tabelproj"
  },
  {
    "timestamp": "2026-03-27T15:43:44.180438",
    "user": "Пользователь",
    "type": "PROJECT_OPEN",
    "description": "Автозагрузка последнего проекта: C:/Users/oniki/Desktop/project_root2/123.tabelproj"
  },
  {
    "timestamp": "2026-03-29T00:08:57.218293",
    "user": "Пользователь",
    "type": "PROJECT_OPEN",
    "description": "Автозагрузка последнего проекта: C:/Users/oniki/Desktop/project_root2/123.tabelproj"
  },
  {
    "timestamp": "2026-03-30T10:19:00.970522",
    "user": "Пользователь",
    "type": "PROJECT_OPEN",
    "description": "Автозагрузка последнего проекта: C:/Users/oniki/Desktop/project_root2/123.tabelproj"
  },
  {
    "timestamp": "2026-03-30T10:19:09.369159",
    "user": "Пользователь",
    "type": "PROJECT_OPEN",
    "description": "Открыт проект: C:/Users/oniki/Desktop/ФОТсо статистикой/2026.tabelproj"
  },
  {
    "timestamp": "2026-03-30T10:20:46.687210",
    "user": "Пользователь",
    "type": "MASS_FILL",
    "description": "Массовое редактирование: 2 ячеек кодом К"
  },
  {
    "timestamp": "2026-03-30T10:20:54.701827",
    "user": "Пользователь",
    "type": "PROJECT_SAVE",
    "description": "Сохранён проект: C:/Users/oniki/Desktop/ФОТсо статистикой/2026.tabelproj"
  },
  {
    "timestamp": "2026-03-30T10:42:12.436281",
    "user": "Пользователь",
    "type": "PROJECT_OPEN",
    "description": "Автозагрузка последнего проекта: C:/Users/oniki/Desktop/ФОТсо статистикой/2026.tabelproj"
  },
  {
    "timestamp": "2026-03-30T10:42:35.707369",
    "user": "Пользователь",
    "type": "PROJECT_OPEN",
    "description": "Открыт проект: C:/Users/oniki/Desktop/ФОТсо статистикой/2026.tabelproj"
  },
  {
    "timestamp": "2026-03-30T10:43:18.682390",
    "user": "Пользователь",
    "type": "VACATIONS_EDITED",
    "description": "Изменён график отпусков"
  },
  {
    "timestamp": "2026-03-30T10:43:29.868957",
    "user": "Пользователь",
    "type": "PROJECT_SAVE",
    "description": "Сохранён проект: C:/Users/oniki/Desktop/ФОТсо статистикой/2026.tabelproj"
  },
  {
    "timestamp": "2026-03-30T11:43:07.111799",
    "user": "Пользователь",
    "type": "PROJECT_OPEN",
    "description": "Автозагрузка последнего проекта: C:/Users/oniki/Desktop/ФОТсо статистикой/2026.tabelproj"
  },
  {
    "timestamp": "2026-03-30T11:48:31.417480",
    "user": "Пользователь",
    "type": "PROJECT_OPEN",
    "description": "Автозагрузка последнего проекта: C:/Users/oniki/Desktop/ФОТсо статистикой/2026.tabelproj"
  },
  {
    "timestamp": "2026-03-30T11:54:13.892657",
    "user": "Пользователь",
    "type": "PROJECT_OPEN",
    "description": "Автозагрузка последнего проекта: C:/Users/oniki/Desktop/ФОТсо статистикой/2026.tabelproj"
  },
  {
    "timestamp": "2026-03-30T13:00:19.741280",
    "user": "Пользователь",
    "type": "PROJECT_OPEN",
    "description": "Автозагрузка последнего проекта: C:/Users/oniki/Desktop/ФОТсо статистикой/2026.tabelproj"
  },
  {
    "timestamp": "2026-03-30T13:07:59.348155",
    "user": "Пользователь",
    "type": "PROJECT_OPEN",
    "description": "Автозагрузка последнего проекта: C:/Users/oniki/Desktop/ФОТсо статистикой/2026.tabelproj"
  },
  {
    "timestamp": "2026-03-30T13:27:41.806993",
    "user": "Пользователь",
    "type": "PROJECT_OPEN",
    "description": "Автозагрузка последнего проекта: C:/Users/oniki/Desktop/ФОТсо статистикой/2026.tabelproj"
  },
  {
    "timestamp": "2026-03-30T13:28:41.882278",
    "user": "Пользователь",
    "type": "PROJECT_OPEN",
    "description": "Автозагрузка последнего проекта: C:/Users/oniki/Desktop/ФОТсо статистикой/2026.tabelproj"
  },
  {
    "timestamp": "2026-03-30T13:56:27.554605",
    "user": "Пользователь",
    "type": "PROJECT_OPEN",
    "description": "Автозагрузка последнего проекта: C:/Users/oniki/Desktop/ФОТсо статистикой/2026.tabelproj"
  },
  {
    "timestamp": "2026-03-30T14:26:28.684332",
    "user": "Пользователь",
    "type": "PROJECT_OPEN",
    "description": "Автозагрузка последнего проекта: C:/Users/oniki/Desktop/ФОТсо статистикой/2026.tabelproj"
  },
  {
    "timestamp": "2026-03-30T14:42:01.310212",
    "user": "Пользователь",
    "type": "PROJECT_OPEN",
    "description": "Автозагрузка последнего проекта: C:/Users/oniki/Desktop/ФОТсо статистикой/2026.tabelproj"
  },
  {
    "timestamp": "2026-03-30T14:55:36.574553",
    "user": "Пользователь",
    "type": "PROJECT_OPEN",
    "description": "Автозагрузка последнего проекта: C:/Users/oniki/Desktop/ФОТсо статистикой/2026.tabelproj"
  },
  {
    "timestamp": "2026-03-30T15:01:51.102806",
    "user": "Пользователь",
    "type": "PROJECT_OPEN",
    "description": "Автозагрузка последнего проекта: C:/Users/oniki/Desktop/ФОТсо статистикой/2026.tabelproj"
  },
  {
    "timestamp": "2026-03-30T15:45:25.689999",
    "user": "Пользователь",
    "type": "PROJECT_OPEN",
    "description": "Автозагрузка последнего проекта: C:/Users/oniki/Desktop/ФОТсо статистикой/2026.tabelproj"
  },
  {
    "timestamp": "2026-03-30T16:00:49.601416",
    "user": "Пользователь",
    "type": "PROJECT_OPEN",
    "description": "Автозагрузка последнего проекта: C:/Users/oniki/Desktop/ФОТсо статистикой/2026.tabelproj"
  },
  {
    "timestamp": "2026-03-30T16:01:52.516862",
    "user": "Пользователь",
    "type": "PROJECT_OPEN",
    "description": "Автозагрузка последнего проекта: C:/Users/oniki/Desktop/ФОТсо статистикой/2026.tabelproj"
  },
  {
    "timestamp": "2026-03-30T16:13:29.011376",
    "user": "Пользователь",
    "type": "PROJECT_OPEN",
    "description": "Автозагрузка последнего проекта: C:/Users/oniki/Desktop/ФОТсо статистикой/2026.tabelproj"
  },
  {
    "timestamp": "2026-03-30T17:02:43.210690",
    "user": "Пользователь",
    "type": "PROJECT_OPEN",
    "description": "Автозагрузка последнего проекта: C:/Users/oniki/Desktop/ФОТсо статистикой/2026.tabelproj"
  },
  {
    "timestamp": "2026-03-30T17:06:08.440240",
    "user": "Пользователь",
    "type": "PROJECT_OPEN",
    "description": "Автозагрузка последнего проекта: C:/Users/oniki/Desktop/ФОТсо статистикой/2026.tabelproj"
  },
  {
    "timestamp": "2026-03-30T17:10:47.918596",
    "user": "Пользователь",
    "type": "PROJECT_OPEN",
    "description": "Автозагрузка последнего проекта: C:/Users/oniki/Desktop/ФОТсо статистикой/2026.tabelproj"
  },
  {
    "timestamp": "2026-03-30T17:18:45.171079",
    "user": "Пользователь",
    "type": "PROJECT_OPEN",
    "description": "Автозагрузка последнего проекта: C:/Users/oniki/Desktop/ФОТсо статистикой/2026.tabelproj"
  },
  {
    "timestamp": "2026-03-30T17:20:48.828547",
    "user": "Пользователь",
    "type": "PROJECT_OPEN",
    "description": "Автозагрузка последнего проекта: C:/Users/oniki/Desktop/ФОТсо статистикой/2026.tabelproj"
  },
  {
    "timestamp": "2026-03-31T10:20:04.174715",
    "user": "Пользователь",
    "type": "PROJECT_OPEN",
    "description": "Автозагрузка последнего проекта: C:/Users/oniki/Desktop/ФОТсо статистикой/2026.tabelproj"
  },
  {
    "timestamp": "2026-03-31T10:30:56.169580",
    "user": "Пользователь",
    "type": "PROJECT_OPEN",
    "description": "Автозагрузка последнего проекта: C:/Users/oniki/Desktop/ФОТсо статистикой/2026.tabelproj"
  },
  {
    "timestamp": "2026-03-31T10:45:16.583592",
    "user": "Пользователь",
    "type": "PROJECT_OPEN",
    "description": "Автозагрузка последнего проекта: C:/Users/oniki/Desktop/ФОТсо статистикой/2026.tabelproj"
  }
]